uodm-0.4.0.dist-info/METADATA
uodm-0.4.0.dist-info/WHEEL
uodm-0.4.0.dist-info/entry_points.txt
uodm-0.4.0.dist-info/licenses/LICENSE
uodm/__init__.py
uodm/change_streams.py
uodm/file_motor.py
uodm/file_motor_filtering.py
uodm/py.typed
uodm/sqlite_motor.py
uodm/types.py
uodm/uodm.py
uodm-0.4.0.dist-info/RECORD
