Metadata-Version: 2.1
Name: uodm
Version: 0.4.0
Summary: ultraminimalistic Python library for simple object-document mappint for asyncronous mongodb
Author-Email: Grigory Bakunov <bobuk@rubedo.cloud>
License: Unlicense
Requires-Python: >=3.11
Requires-Dist: pydantic>=2.10.2
Requires-Dist: motor>=3.4.0
Provides-Extra: orjson
Requires-Dist: orjson>=3.9.10; extra == "orjson"
Provides-Extra: sqlite
Requires-Dist: aiosqlite>=0.19.0; extra == "sqlite"
